MANIFEST.in
medialog.kuliadentheme-configure.zcml
setup.cfg
setup.py
docs/HISTORY.txt
docs/INSTALL.txt
docs/LICENSE.GPL
docs/LICENSE.txt
medialog/__init__.py
medialog.kuliadentheme.egg-info/PKG-INFO
medialog.kuliadentheme.egg-info/SOURCES.txt
medialog.kuliadentheme.egg-info/dependency_links.txt
medialog.kuliadentheme.egg-info/entry_points.txt
medialog.kuliadentheme.egg-info/namespace_packages.txt
medialog.kuliadentheme.egg-info/not-zip-safe
medialog.kuliadentheme.egg-info/paster_plugins.txt
medialog.kuliadentheme.egg-info/requires.txt
medialog.kuliadentheme.egg-info/top_level.txt
medialog/kuliadentheme/__init__.py
medialog/kuliadentheme/configure.zcml
medialog/kuliadentheme/profiles.zcml
medialog/kuliadentheme/setuphandlers.py
medialog/kuliadentheme/skins.zcml
medialog/kuliadentheme/tests.py
medialog/kuliadentheme/version.txt
medialog/kuliadentheme/browser/__init__.py
medialog/kuliadentheme/browser/configure.zcml
medialog/kuliadentheme/browser/interfaces.py
medialog/kuliadentheme/browser/viewlet.pt
medialog/kuliadentheme/browser/viewlets.py
medialog/kuliadentheme/browser/images/README.txt
medialog/kuliadentheme/browser/stylesheets/README.txt
medialog/kuliadentheme/browser/stylesheets/main.css
medialog/kuliadentheme/profiles/default/cssregistry.xml
medialog/kuliadentheme/profiles/default/import_steps.xml
medialog/kuliadentheme/profiles/default/jsregistry.xml
medialog/kuliadentheme/profiles/default/medialog.kuliadentheme_various.txt
medialog/kuliadentheme/profiles/default/metadata.xml
medialog/kuliadentheme/profiles/default/portlets.xml
medialog/kuliadentheme/profiles/default/skins.xml
medialog/kuliadentheme/profiles/default/viewlets.xml
medialog/kuliadentheme/skins/medialog_kuliadentheme_custom_images/000event.jpg
medialog/kuliadentheme/skins/medialog_kuliadentheme_custom_images/000forlop.jpg
medialog/kuliadentheme/skins/medialog_kuliadentheme_custom_images/000forlopv.jpg
medialog/kuliadentheme/skins/medialog_kuliadentheme_custom_images/000forlopvII.jpg
medialog/kuliadentheme/skins/medialog_kuliadentheme_custom_images/000head30.jpg
medialog/kuliadentheme/skins/medialog_kuliadentheme_custom_images/000lique.png
medialog/kuliadentheme/skins/medialog_kuliadentheme_custom_images/000liqueII.png
medialog/kuliadentheme/skins/medialog_kuliadentheme_custom_images/000mail.jpg
medialog/kuliadentheme/skins/medialog_kuliadentheme_custom_images/000mail_icon.jpg
