Metadata-Version: 1.0
Name: medialog.kuliadentheme
Version: 1.2dev-r116337
Summary: An installable theme for Plone 3.0
Home-page: http://svn.plone.org/svn/collective/
Author: Espen Moe-Nilssen
Author-email: espen@medialog.no
License: GPL
Keywords: web zope plone theme
Platform: UNKNOWN
Classifier: Framework :: Plone
Classifier: Programming Language :: Python
Classifier: Topic :: Software Development :: Libraries :: Python Modules
